<?xml version="1.0" encoding="utf-8"?>
<Document>
  <Engineering version="V17" />
  <DocumentInfo>
    <Created>2022-03-12T16:05:31.4284412Z</Created>
    <ExportSetting>WithDefaults</ExportSetting>
    <InstalledProducts>
      <Product>
        <DisplayName>Totally Integrated Automation Portal</DisplayName>
        <DisplayVersion>V17</DisplayVersion>
      </Product>
      <OptionPackage>
        <DisplayName>TIA Portal Openness</DisplayName>
        <DisplayVersion>V17</DisplayVersion>
      </OptionPackage>
      <OptionPackage>
        <DisplayName>TIA Portal Version Control Interface</DisplayName>
        <DisplayVersion>V17</DisplayVersion>
      </OptionPackage>
      <Product>
        <DisplayName>STEP 7 Professional</DisplayName>
        <DisplayVersion>V17</DisplayVersion>
      </Product>
      <OptionPackage>
        <DisplayName>STEP 7 Safety</DisplayName>
        <DisplayVersion>V17</DisplayVersion>
      </OptionPackage>
      <Product>
        <DisplayName>WinCC Advanced / Unified PC</DisplayName>
        <DisplayVersion>V17</DisplayVersion>
      </Product>
    </InstalledProducts>
  </DocumentInfo>
  <SW.Blocks.GlobalDB ID="0">
    <AttributeList>
      <AutoNumber>true</AutoNumber>
      <DBAccessibleFromOPCUA>true</DBAccessibleFromOPCUA>
      <DBAccessibleFromWebserver>true</DBAccessibleFromWebserver>
      <HeaderAuthor>tech.team.motioncontrol@siemens.com</HeaderAuthor>
      <HeaderFamily>CPG</HeaderFamily>
      <HeaderName />
      <HeaderVersion>1.0</HeaderVersion>
      <Interface><Sections xmlns="http://www.siemens.com/automation/Openness/SW/Interface/v5">
  <Section Name="Static">
    <Member Name="machineSpeedSP" Datatype="Real" Remanence="NonRetain" Accessibility="Public"><AttributeList><BooleanAttribute Name="ExternalAccessible" SystemDefined="true">true</BooleanAttribute><BooleanAttribute Name="ExternalVisible" SystemDefined="true">true</BooleanAttribute><BooleanAttribute Name="ExternalWritable" SystemDefined="true">true</BooleanAttribute><BooleanAttribute Name="SetPoint" SystemDefined="true">false</BooleanAttribute></AttributeList><Comment><MultiLanguageText Lang="en-US">Machine Speed Setpoint (product per min)</MultiLanguageText><MultiLanguageText Lang="de-DE">Machine Speed Setpoint (product per min)</MultiLanguageText></Comment><StartValue>20.0</StartValue></Member>
    <Member Name="machineSpeedPV" Datatype="Real" Remanence="NonRetain" Accessibility="Public"><AttributeList><BooleanAttribute Name="ExternalAccessible" SystemDefined="true">true</BooleanAttribute><BooleanAttribute Name="ExternalVisible" SystemDefined="true">true</BooleanAttribute><BooleanAttribute Name="ExternalWritable" SystemDefined="true">false</BooleanAttribute><BooleanAttribute Name="SetPoint" SystemDefined="true">false</BooleanAttribute></AttributeList><Comment><MultiLanguageText Lang="en-US">Machine Speed Actual (product per min)</MultiLanguageText><MultiLanguageText Lang="de-DE">Machine Speed Actual (product per min)</MultiLanguageText></Comment></Member>
  </Section>
</Sections></Interface>
      <IsOnlyStoredInLoadMemory>false</IsOnlyStoredInLoadMemory>
      <IsRetainMemResEnabled>false</IsRetainMemResEnabled>
      <IsWriteProtectedInAS>false</IsWriteProtectedInAS>
      <MemoryLayout>Optimized</MemoryLayout>
      <MemoryReserve>0</MemoryReserve>
      <Name>HMI_Data_Custom</Name>
      <Number>31616</Number>
      <ProgrammingLanguage>DB</ProgrammingLanguage>
    </AttributeList>
    <ObjectList>
      <MultilingualText ID="1" CompositionName="Comment">
        <ObjectList>
          <MultilingualTextItem ID="2" CompositionName="Items">
            <AttributeList>
              <Culture>en-US</Culture>
              <Text>Support: tech.team.motioncontrol@siemens.com
Fax: +49 (0) 9131/98-1297</Text>
            </AttributeList>
          </MultilingualTextItem>
          <MultilingualTextItem ID="3" CompositionName="Items">
            <AttributeList>
              <Culture>de-DE</Culture>
              <Text>Support: tech.team.motioncontrol@siemens.com
Fax: +49 (0) 9131/98-1297</Text>
            </AttributeList>
          </MultilingualTextItem>
        </ObjectList>
      </MultilingualText>
      <MultilingualText ID="4" CompositionName="Title">
        <ObjectList>
          <MultilingualTextItem ID="5" CompositionName="Items">
            <AttributeList>
              <Culture>en-US</Culture>
              <Text>CPG_HMI_Data_Custom</Text>
            </AttributeList>
          </MultilingualTextItem>
          <MultilingualTextItem ID="6" CompositionName="Items">
            <AttributeList>
              <Culture>de-DE</Culture>
              <Text>CPG_HMI_Data_Custom</Text>
            </AttributeList>
          </MultilingualTextItem>
        </ObjectList>
      </MultilingualText>
    </ObjectList>
  </SW.Blocks.GlobalDB>
</Document>